<?xml version="1.0" encoding="UTF-8"?>
<featureType>
  <id><![CDATA[da19f6d388f5a3987e188bf50f2eb172]]></id>
  <typeName><![CDATA[N_prefixTri_ENJEU_CRISE_L]]></typeName>
  <description><![CDATA[]]></description>
  <attributes>
    <attribute>
      <regexp><![CDATA[]]></regexp>
      <id><![CDATA[061fe7d7a2f27aeb61ef56638387fbbd]]></id>
      <name><![CDATA[CATEGORIE]]></name>
      <description><![CDATA[Valeur vide interdite]]></description>
      <type><![CDATA[String]]></type>
      <nullable>false</nullable>
      <listOfValues>
        <value><![CDATA[11]]></value>
        <value><![CDATA[99]]></value>
        <value><![CDATA[98]]></value>
        <value><![CDATA[01]]></value>
        <value><![CDATA[15]]></value>
        <value><![CDATA[03]]></value>
        <value><![CDATA[04]]></value>
        <value><![CDATA[06]]></value>
        <value><![CDATA[05]]></value>
        <value><![CDATA[07]]></value>
        <value><![CDATA[08]]></value>
        <value><![CDATA[10]]></value>
        <value><![CDATA[09]]></value>
        <value><![CDATA[12]]></value>
        <value><![CDATA[13]]></value>
        <value><![CDATA[14]]></value>
        <value><![CDATA[02]]></value>
      </listOfValues>
    </attribute>
    <attribute>
      <regexp><![CDATA[^[0-9]{4}[a-z]*$]]></regexp>
      <id><![CDATA[4d9f67cb77fbe2f6905014f17d012ff6]]></id>
      <name><![CDATA[CODCOVADIS]]></name>
      <description><![CDATA[Cf. nomenclature COVADIS standard PPRN (annexe D.1)]]></description>
      <type><![CDATA[String]]></type>
      <nullable>true</nullable>
    </attribute>
    <attribute>
      <id><![CDATA[725fa9a6ed4494febd44145a87e30628]]></id>
      <name><![CDATA[WKT]]></name>
      <type><![CDATA[MultiLineString]]></type>
      <nullable>false</nullable>
    </attribute>
    <attribute>
      <regexp><![CDATA[]]></regexp>
      <id><![CDATA[b3f27b91a17f21372b69f435e9efd149]]></id>
      <name><![CDATA[EST_REF]]></name>
      <description><![CDATA[]]></description>
      <type><![CDATA[String]]></type>
      <nullable>true</nullable>
      <listOfValues>
        <value><![CDATA[Vrai]]></value>
        <value><![CDATA[Faux]]></value>
      </listOfValues>
    </attribute>
    <attribute>
      <regexp><![CDATA[]]></regexp>
      <id><![CDATA[b5fb20e940f5188dddef098ab7ab9685]]></id>
      <name><![CDATA[VER_SI_EXT]]></name>
      <description><![CDATA[]]></description>
      <type><![CDATA[String]]></type>
      <nullable>true</nullable>
    </attribute>
    <attribute>
      <regexp><![CDATA[]]></regexp>
      <id><![CDATA[bcd6a7a4457666e05c8d6db994a7be43]]></id>
      <name><![CDATA[DATIMPORT]]></name>
      <description><![CDATA[]]></description>
      <type><![CDATA[Date]]></type>
      <nullable>true</nullable>
    </attribute>
    <attribute>
      <regexp><![CDATA[]]></regexp>
      <id><![CDATA[c34a9a29afaad786b68499a2cff11555]]></id>
      <name><![CDATA[ID_SI_EXT]]></name>
      <description><![CDATA[Valeur vide interdite]]></description>
      <type><![CDATA[String]]></type>
      <nullable>false</nullable>
    </attribute>
    <attribute>
      <regexp><![CDATA[]]></regexp>
      <id><![CDATA[db9a4e2f2fe19f5dcf085a6a6b32682e]]></id>
      <name><![CDATA[NOM_SI_EXT]]></name>
      <description><![CDATA[Valeur vide interdite]]></description>
      <type><![CDATA[String]]></type>
      <nullable>false</nullable>
    </attribute>
  </attributes>
</featureType>
